coldplay/__init__.py
coldplay/task.py
coldplay-0.0.3.dist-info/METADATA
coldplay-0.0.3.dist-info/WHEEL
coldplay-0.0.3.dist-info/licenses/LICENSE.txt
coldplay-0.0.3.dist-info/RECORD
