Metadata-Version: 2.3
Name: coldplay
Version: 0.0.3
Summary: This is a package that logs console output
Project-URL: Documentation, https://github.com/liam/coldplay#readme
Project-URL: Issues, https://github.com/liam/coldplay/issues
Project-URL: Source, https://github.com/liam/coldplay
Author-email: liam <liam@limxdynamics.com>
License-Expression: MIT
License-File: LICENSE.txt
Classifier: Development Status :: 4 - Beta
Classifier: License :: OSI Approved :: MIT License
Classifier: Operating System :: OS Independent
Classifier: Programming Language :: Python
Classifier: Programming Language :: Python :: 3.8
Classifier: Programming Language :: Python :: Implementation :: CPython
Classifier: Programming Language :: Python :: Implementation :: PyPy
Requires-Python: >=3.8
